setup.py
vpm.py
test/test_vpm.py
vpm.egg-info/PKG-INFO
vpm.egg-info/SOURCES.txt
vpm.egg-info/dependency_links.txt
vpm.egg-info/entry_points.txt
vpm.egg-info/requires.txt
vpm.egg-info/top_level.txt