Metadata-Version: 1.1
Name: vpm
Version: 0.0.2
Summary: 
